pyplotter/__init__.py
pyplotter/pyplotter.py
pyplotter/mathjax/tex-chtml.js
pyplotter/mathjax/output/chtml.js
pyplotter/mathjax/output/chtml/fonts/tex.js
pyplotter/mathjax/output/chtml/fonts/woff-v2/MathJax_AMS-Regular.woff
pyplotter/mathjax/output/chtml/fonts/woff-v2/MathJax_Calligraphic-Bold.woff
pyplotter/mathjax/output/chtml/fonts/woff-v2/MathJax_Calligraphic-Regular.woff
pyplotter/mathjax/output/chtml/fonts/woff-v2/MathJax_Fraktur-Bold.woff
pyplotter/mathjax/output/chtml/fonts/woff-v2/MathJax_Fraktur-Regular.woff
pyplotter/mathjax/output/chtml/fonts/woff-v2/MathJax_Main-Bold.woff
pyplotter/mathjax/output/chtml/fonts/woff-v2/MathJax_Main-Italic.woff
pyplotter/mathjax/output/chtml/fonts/woff-v2/MathJax_Main-Regular.woff
pyplotter/mathjax/output/chtml/fonts/woff-v2/MathJax_Math-BoldItalic.woff
pyplotter/mathjax/output/chtml/fonts/woff-v2/MathJax_Math-Italic.woff
pyplotter/mathjax/output/chtml/fonts/woff-v2/MathJax_Math-Regular.woff
pyplotter/mathjax/output/chtml/fonts/woff-v2/MathJax_SansSerif-Bold.woff
pyplotter/mathjax/output/chtml/fonts/woff-v2/MathJax_SansSerif-Italic.woff
pyplotter/mathjax/output/chtml/fonts/woff-v2/MathJax_SansSerif-Regular.woff
pyplotter/mathjax/output/chtml/fonts/woff-v2/MathJax_Script-Regular.woff
pyplotter/mathjax/output/chtml/fonts/woff-v2/MathJax_Size1-Regular.woff
pyplotter/mathjax/output/chtml/fonts/woff-v2/MathJax_Size2-Regular.woff
pyplotter/mathjax/output/chtml/fonts/woff-v2/MathJax_Size3-Regular.woff
pyplotter/mathjax/output/chtml/fonts/woff-v2/MathJax_Size4-Regular.woff
pyplotter/mathjax/output/chtml/fonts/woff-v2/MathJax_Typewriter-Regular.woff
pyplotter/mathjax/output/chtml/fonts/woff-v2/MathJax_Vector-Bold.woff
pyplotter/mathjax/output/chtml/fonts/woff-v2/MathJax_Vector-Regular.woff
pyplotter/mathjax/output/chtml/fonts/woff-v2/MathJax_Zero.woff
pyplotter/sources/__init__.py
pyplotter/sources/config.py
pyplotter/sources/functions.py
pyplotter/sources/main.py
pyplotter/sources/palettes.py
pyplotter/sources/pyqtgraph.py
pyplotter-0.3.8.dist-info/LICENSE
pyplotter-0.3.8.dist-info/METADATA
pyplotter-0.3.8.dist-info/WHEEL
pyplotter-0.3.8.dist-info/entry_points.txt
pyplotter-0.3.8.dist-info/top_level.txt
pyplotter-0.3.8.dist-info/RECORD
