Metadata-Version: 2.1
Name: pyplotter
Version: 0.3.8
Summary: A data browser and vizualizer for QCoDes database, csv, npz, s2p and BlueFors logging files.
Home-page: https://github.com/pyplotter/pyplotter
Author: Étienne Dumur
Author-email: etienne.dumur@cea.fr
Maintainer: Étienne Dumur
Maintainer-email: etienne.dumur@cea.fr
License: MIT
Classifier: Programming Language :: Python :: 3
Classifier: Intended Audience :: Science/Research
Classifier: Operating System :: OS Independent
Classifier: Topic :: Scientific/Engineering
Requires-Python: >=3.8
License-File: LICENSE
Requires-Dist: qdarkstyle
Requires-Dist: lmfit
Requires-Dist: multiprocess
Requires-Dist: numpy >=1.17.0
Requires-Dist: pandas >=1.0.0
Requires-Dist: platformdirs
Requires-Dist: pyopengl
Requires-Dist: pyqt5
Requires-Dist: pyqt5-sip
Requires-Dist: pyqtwebengine
Requires-Dist: pyqtgraph >=0.12.3
Requires-Dist: qcodes >=0.26.0
Requires-Dist: scikit-rf
Requires-Dist: scipy
